search_this/__init__.py
search_this/main.py
search_this/start.py
search_this/utils.py
search_this-0.4.2.dist-info/METADATA
search_this-0.4.2.dist-info/WHEEL
search_this-0.4.2.dist-info/entry_points.txt
search_this-0.4.2.dist-info/top_level.txt
search_this-0.4.2.dist-info/RECORD
